tk_image_cropper/__init__.py
tk_image_cropper/image_cropper.py
tk_image_cropper-0.1.0.dist-info/METADATA
tk_image_cropper-0.1.0.dist-info/WHEEL
tk_image_cropper-0.1.0.dist-info/top_level.txt
tk_image_cropper-0.1.0.dist-info/RECORD
