Metadata-Version: 2.1
Name: tk-image-cropper
Version: 0.1.0
Summary: A simple program that uses a Tkinter GUI to crop an image to specified dimensions.
Home-page: https://github.com/Stefan4472/Stefans-Blog
Author: Stefan Kussmaul
Author-email: stefan@stefanonsoftware.com
License: MIT
Keywords: tkinter,image,cropping
Classifier: License :: OSI Approved :: MIT License
Classifier: Programming Language :: Python :: 3
Requires-Dist: Pillow
